magicbag/__init__.py
magicbag/_version.py
magicbag/mock/__init__.py
magicbag/mock/date.py
magicbag/mock/decimal.py
magicbag/mock/int.py
magicbag/mock/time.py
magicbag/string/__init__.py
magicbag/string/check.py
magicbag-0.0.20.dist-info/LICENSE
magicbag-0.0.20.dist-info/METADATA
magicbag-0.0.20.dist-info/WHEEL
magicbag-0.0.20.dist-info/top_level.txt
magicbag-0.0.20.dist-info/RECORD
